mans_to_es/__init__.py
mans_to_es/mans_to_es.py
mans_to_es-1.6.dist-info/AUTHORS
mans_to_es-1.6.dist-info/LICENSE
mans_to_es-1.6.dist-info/METADATA
mans_to_es-1.6.dist-info/WHEEL
mans_to_es-1.6.dist-info/entry_points.txt
mans_to_es-1.6.dist-info/top_level.txt
mans_to_es-1.6.dist-info/RECORD
