Metadata-Version: 2.1
Name: mans-to-es
Version: 1.6
Summary: Send .mans to ElasticSearch
Home-page: https://github.com/LDO-CERT/mans_to_es
Author: LDO-CERT
Author-email: gcert@leonardocompany.com
License: Apache License, Version 2.0
Platform: UNKNOWN
Classifier: Programming Language :: Python :: 3
Classifier: Operating System :: OS Independent
Requires-Dist: certifi (>=2017.7.27.1)
Requires-Dist: elasticsearch (>=7.5.1)
Requires-Dist: numpy (>=1.16.6)
Requires-Dist: pandas (>=0.24.2)
Requires-Dist: python-dateutil (==2.8.1)
Requires-Dist: pytz (==2020.1)
Requires-Dist: six (==1.12.0)
Requires-Dist: urllib3 (==1.25.9)
Requires-Dist: xmltodict (==0.12.0)
Requires-Dist: ciso8601 (>=2.1.1)
Requires-Dist: billiard (==3.6.3.0)
